qbtrain/__init__.py
qbtrain/agents/__init__.py
qbtrain/ai/__init__.py
qbtrain/ai/embeddings/__init__.py
qbtrain/ai/llm/__init__.py
qbtrain/ai/llm/azure_foundry_client.py
qbtrain/ai/llm/base_llm_client.py
qbtrain/ai/llm/bedrock_client.py
qbtrain/ai/llm/gcp_model_garden_client.py
qbtrain/ai/llm/huggingface_client.py
qbtrain/ai/llm/ollama_client.py
qbtrain/ai/llm/openai_client.py
qbtrain/ai/llm/registry.py
qbtrain-0.1.2.dist-info/licenses/LICENSE
qbtrain-0.1.2.dist-info/METADATA
qbtrain-0.1.2.dist-info/WHEEL
qbtrain-0.1.2.dist-info/top_level.txt
qbtrain-0.1.2.dist-info/RECORD
