Metadata-Version: 2.4
Name: qbtrain
Version: 0.1.2
Summary: Tools for training and serving models (replace with a short description)
Author: Pavan Reddy
Keywords: training,ml,qbtrain
Classifier: Development Status :: 4 - Beta
Classifier: Intended Audience :: Developers
Classifier: License :: OSI Approved :: MIT License
Classifier: Programming Language :: Python
Classifier: Programming Language :: Python :: 3
Classifier: Programming Language :: Python :: 3.11
Classifier: Operating System :: OS Independent
Requires-Python: >=3.11
License-File: LICENSE
Requires-Dist: Django>=4.2
Requires-Dist: django-cors-headers
Requires-Dist: djangorestframework
Requires-Dist: drf-spectacular
Requires-Dist: gunicorn
Requires-Dist: boto3
Requires-Dist: ollama
Dynamic: license-file
